tc_multidir/__init__.py
tc_multidir/loader.py
leukeleu_thumbor_multidir-1.0.0.dist-info/LICENSE
leukeleu_thumbor_multidir-1.0.0.dist-info/METADATA
leukeleu_thumbor_multidir-1.0.0.dist-info/WHEEL
leukeleu_thumbor_multidir-1.0.0.dist-info/top_level.txt
leukeleu_thumbor_multidir-1.0.0.dist-info/RECORD
