Metadata-Version: 2.1
Name: leukeleu-thumbor-multidir
Version: 1.0.0
Summary: Thumbor file loader that support multiple source paths
Home-page: https://github.com/leukleu/leukeleu-thumbor-multidir
Author: Jaap Roes
Author-email: jroes@leukeleu.nl
License: MIT
Keywords: thumbor file loader multiple source directories
Classifier: License :: OSI Approved :: MIT License
Classifier: Development Status :: 5 - Production/Stable
Requires-Python: >=3.8
License-File: LICENSE
Requires-Dist: thumbor (<8,>=7)
Provides-Extra: test
Requires-Dist: black (~=23.1) ; extra == 'test'
Requires-Dist: check-manifest (==0.49) ; extra == 'test'
Requires-Dist: flake8 (~=6.0) ; extra == 'test'
Requires-Dist: flake8-assertive (~=2.1) ; extra == 'test'
Requires-Dist: flake8-black (~=0.3.0) ; extra == 'test'
Requires-Dist: flake8-bugbear (~=23.3) ; extra == 'test'
Requires-Dist: flake8-isort (~=6.0) ; extra == 'test'
Requires-Dist: pep8-naming (~=0.13) ; extra == 'test'
Requires-Dist: coverage (~=7.2) ; extra == 'test'
Requires-Dist: preggy (~=1.4.4) ; extra == 'test'
